tmep/__init__.py
tmep/doc.py
tmep/format.py
tmep/functions.py
tmep/help.rst
tmep/py.typed
tmep/template.py
tmep/types.py
tmep-3.0.1.dist-info/LICENSE
tmep-3.0.1.dist-info/METADATA
tmep-3.0.1.dist-info/WHEEL
tmep-3.0.1.dist-info/entry_points.txt
tmep-3.0.1.dist-info/RECORD
